{
	"id": "9c2d7f4f-2892-9ecf-cd66-70e91a59da83",
	"name": "Dog API",
	"description": "",
	"order": [
		"ef93382b-2cdc-9c97-c1ea-10f2b578e8f9",
		"0efbcc4a-ff0b-d2ee-53f4-094233ce8a66",
		"54a5c975-c4aa-326a-88ff-032e8552c1d3",
		"4a70e411-ad3f-eb63-14fa-c3d2ee5b2919"
	],
	"folders": [],
	"folders_order": [],
	"timestamp": 1551469317051,
	"owner": "6803172",
	"public": false,
	"requests": [
		{
			"id": "0efbcc4a-ff0b-d2ee-53f4-094233ce8a66",
			"headers": "",
			"headerData": [],
			"url": "https://dog.ceo/api/breed/retriever/list",
			"queryParams": [],
			"pathVariables": {},
			"pathVariableData": [],
			"preRequestScript": null,
			"method": "POST",
			"collectionId": "9c2d7f4f-2892-9ecf-cd66-70e91a59da83",
			"data": null,
			"dataMode": "params",
			"name": "Get_SubBreeds",
			"description": "",
			"descriptionFormat": "html",
			"time": 1551469628079,
			"version": 2,
			"responses": [],
			"tests": null,
			"currentHelper": "normal",
			"helperAttributes": {}
		},
		{
			"id": "4a70e411-ad3f-eb63-14fa-c3d2ee5b2919",
			"headers": "",
			"headerData": [],
			"url": "https://dog.ceo/api/breeds/list/all",
			"queryParams": [],
			"preRequestScript": null,
			"pathVariables": {},
			"pathVariableData": [],
			"method": "POST",
			"data": null,
			"dataMode": "params",
			"tests": null,
			"currentHelper": "normal",
			"helperAttributes": {},
			"time": 1551470741157,
			"name": "Verify_Retriever_Exists",
			"description": "",
			"collectionId": "9c2d7f4f-2892-9ecf-cd66-70e91a59da83",
			"responses": []
		},
		{
			"id": "54a5c975-c4aa-326a-88ff-032e8552c1d3",
			"headers": "",
			"headerData": [],
			"url": "https://dog.ceo/api/breed/retriever/golden/images/random",
			"queryParams": [],
			"pathVariables": {},
			"pathVariableData": [],
			"preRequestScript": null,
			"method": "POST",
			"collectionId": "9c2d7f4f-2892-9ecf-cd66-70e91a59da83",
			"data": null,
			"dataMode": "params",
			"name": "Get_RandomImage_bySubBreed",
			"description": "",
			"descriptionFormat": "html",
			"time": 1551470235933,
			"version": 2,
			"responses": [],
			"tests": null,
			"currentHelper": "normal",
			"helperAttributes": {}
		},
		{
			"id": "ef93382b-2cdc-9c97-c1ea-10f2b578e8f9",
			"headers": "",
			"headerData": [],
			"url": "https://dog.ceo/api/breeds/list/all",
			"queryParams": [],
			"preRequestScript": null,
			"pathVariables": {},
			"pathVariableData": [],
			"method": "POST",
			"data": null,
			"dataMode": "params",
			"version": 2,
			"tests": null,
			"currentHelper": "normal",
			"helperAttributes": {},
			"time": 1551469397119,
			"name": "Get_Breeds",
			"description": "",
			"collectionId": "9c2d7f4f-2892-9ecf-cd66-70e91a59da83",
			"responses": []
		}
	]
}